Metadata-Version: 1.0
Name: global-star
Version: 0.1.2
Summary: Python automatic operation and maintenance platform
Home-page: https://www.cnblogs.com/yinzhengjie/p/14124623.html
Author: yinzhengjie
Author-email: y1053419035@qq.com
License: UNKNOWN
Platform: UNKNOWN
